Metadata-Version: 2.1
Name: glucose-stats
Version: 0.0.6
Summary: Calculate glucose statistics from continuous glucose monitoring data
Home-page: https://github.com/evavanweenen/glucose-stats
Author: Eva van Weenen
Author-email: evanweenen@ethz.ch
License: MIT
License-File: LICENSE
